MANIFEST.in
README.md
VERSION
requirements.txt
setup.py
safe_extractor/__init__.py
safe_extractor/safe_extractor.py
safe_extractor.egg-info/PKG-INFO
safe_extractor.egg-info/SOURCES.txt
safe_extractor.egg-info/dependency_links.txt
safe_extractor.egg-info/entry_points.txt
safe_extractor.egg-info/requires.txt
safe_extractor.egg-info/top_level.txt
safe_extractor/../README.md
safe_extractor/../VERSION
safe_extractor/../requirements.txt