Metadata-Version: 1.1
Name: safe-extractor
Version: 0.0.9
Summary: Some code that supposedly extracts zip/tar archives safely.
Home-page: https://github.com/jonathanporta/safe_extractor
Author: Jonathan Porta
Author-email: jonathan@jonathanPorta.com
License: MIT
Keywords: tar zip extract archive
Platform: UNKNOWN
Classifier: Development Status :: 5 - Production/Stable
Classifier: Intended Audience :: Developers
Classifier: Topic :: Software Development :: Build Tools
Classifier: License :: OSI Approved :: MIT License
Classifier: Programming Language :: Python :: 3.6
